kyro/__init__.py
kyro/_auth.py
kyro/_config.py
kyro/_serialization.py
kyro/_session.py
kyro/_version.py
kyro/exceptions.py
kyro/rest/__init__.py
kyro/rest/client.py
kyro/rest/api/__init__.py
kyro/rest/api/events.py
kyro/rest/api/exchange.py
kyro/rest/api/markets.py
kyro/rest/api/orders.py
kyro/rest/api/portfolio.py
kyro/rest/api/search.py
kyro-0.1.2.dist-info/licenses/LICENSE.md
kyro-0.1.2.dist-info/METADATA
kyro-0.1.2.dist-info/WHEEL
kyro-0.1.2.dist-info/top_level.txt
kyro-0.1.2.dist-info/RECORD
