Metadata-Version: 2.4
Name: kyro
Version: 0.1.2
Summary: Async Kalshi API client (aiohttp, Pydantic). Library for building apps.
Author: Kyro
License: MIT
Project-URL: Repository, https://github.com/UTXOnly/kyro
Keywords: async,aiohttp,kalshi,rest,pydantic
Classifier: Development Status :: 3 - Alpha
Classifier: Intended Audience :: Developers
Classifier: License :: OSI Approved :: MIT License
Classifier: Programming Language :: Python :: 3
Classifier: Programming Language :: Python :: 3.10
Classifier: Programming Language :: Python :: 3.11
Classifier: Programming Language :: Python :: 3.12
Classifier: Topic :: Internet :: WWW/HTTP
Requires-Python: >=3.10
License-File: LICENSE.md
Requires-Dist: aiohttp>=3.9.0
Requires-Dist: pydantic>=2.0
Requires-Dist: cryptography>=41.0
Requires-Dist: python-dotenv>=1.0.0
Provides-Extra: dev
Requires-Dist: pytest>=7.0; extra == "dev"
Requires-Dist: pytest-asyncio>=0.21; extra == "dev"
Requires-Dist: pytest-cov>=4.0; extra == "dev"
Requires-Dist: ruff>=0.1.0; extra == "dev"
Requires-Dist: black>=24.0; extra == "dev"
Provides-Extra: bench
Requires-Dist: pytest-benchmark>=4.0; extra == "bench"
Dynamic: license-file
